insultgenerator/__init__.py
insultgenerator/phrases.py
insultgenerator/tests.py
insultgenerator/words.py
insultgenerator/wordlists/insulting_adjectives.txt
insultgenerator/wordlists/nouns.txt
insultgenerator/wordlists/past_tense_verbs.txt
insultgenerator-1.0.3.dist-info/LICENSE
insultgenerator-1.0.3.dist-info/METADATA
insultgenerator-1.0.3.dist-info/WHEEL
insultgenerator-1.0.3.dist-info/top_level.txt
insultgenerator-1.0.3.dist-info/RECORD
