Metadata-Version: 2.1
Name: insultgenerator
Version: 1.0.3
Summary: Random insult generator
Home-page: https://github.com/tr00st/insult_generator
Author: James Cheese
Author-email: trust@tr00st.co.uk
License: MIT
Platform: UNKNOWN
Classifier: Development Status :: 5 - Production/Stable
Classifier: Programming Language :: Python :: 2.7
Classifier: Programming Language :: Python :: 3
Classifier: Programming Language :: Python :: 3.4
Classifier: Programming Language :: Python :: 3.5
Classifier: Programming Language :: Python :: 3.6
Classifier: Programming Language :: Python :: 3.7
Classifier: License :: OSI Approved :: MIT License
